zope/security/__init__.py
zope/security/_compat.py
zope/security/_definitions.py
zope/security/_proxy.c
zope/security/_proxy.cpython-312-aarch64-linux-gnu.so
zope/security/_zope_security_checker.c
zope/security/_zope_security_checker.cpython-312-aarch64-linux-gnu.so
zope/security/adapter.py
zope/security/checker.py
zope/security/configure.zcml
zope/security/decorator.py
zope/security/i18n.py
zope/security/interfaces.py
zope/security/management.py
zope/security/meta.zcml
zope/security/metaconfigure.py
zope/security/metadirectives.py
zope/security/permission.py
zope/security/permissions.zcml
zope/security/protectclass.py
zope/security/proxy.py
zope/security/simplepolicies.py
zope/security/testing.py
zope/security/zcml.py
zope/security/examples/sandbox.py
zope/security/examples/sandbox_security.py
zope/security/tests/__init__.py
zope/security/tests/exampleclass.py
zope/security/tests/module.py
zope/security/tests/redefineperms.zcml
zope/security/tests/test_adapter.py
zope/security/tests/test_checker.py
zope/security/tests/test_compile_flags.py
zope/security/tests/test_decorator.py
zope/security/tests/test_location.py
zope/security/tests/test_management.py
zope/security/tests/test_metaconfigure.py
zope/security/tests/test_permission.py
zope/security/tests/test_protectclass.py
zope/security/tests/test_proxy.py
zope/security/tests/test_simpleinteraction.py
zope/security/tests/test_simplepolicies.py
zope/security/tests/test_testing.py
zope/security/tests/test_zcml.py
zope/security/tests/test_zcml_functest.py
zope_security-8.1.dist-info/METADATA
zope_security-8.1.dist-info/WHEEL
zope_security-8.1.dist-info/top_level.txt
zope_security-8.1.dist-info/RECORD
zope_security-8.1.dist-info/licenses/LICENSE.txt
